{
  "import": [
    { "path": "moonbitlang/async/fs", "alias": "async_fs" },
    { "path": "moonbitlang/async/http", "alias": "async_http" },
    { "path": "moonbitlang/async/socket", "alias": "async_socket" },
    { "path": "f4ah6o/engenis/src/html", "alias": "html" },
    { "path": "f4ah6o/engenis/src/hda", "alias": "hda" },
    { "path": "f4ah6o/engenis/src/router", "alias": "router" }
  ],
  "warn-list": "-29",
  "targets": {
    "async_bridge_native.mbt": ["native"],
    "server.mbt": ["native"],
    "counter.mbt": ["native"],
    "assets.mbt": ["native"]
  }
}
